{
  "entity_name": "CSPPaymentRequest",
  "supabase_table": "csp_paymentrequest",
  "schema": {
    "properties": {
      "request_id": {
        "type": "string"
      },
      "csp_id": {
        "type": "string"
      },
      "customer_id": {
        "type": "string"
      },
      "amount": {
        "type": "number"
      },
      "payment_type": {
        "type": "string"
      },
      "status": {
        "type": "string",
        "enum": [
          "Pending",
          "Approved",
          "Rejected",
          "Completed"
        ]
      }
    },
    "type": "object"
  },
  "sync": {
    "realtime": true,
    "supabase_enabled": true
  }
}